{"path":"IDVGVD100mV","deepCounters":{"total":9,"images":9,"files":9},"counters":{"total":9,"images":9,"files":9},"thumb":{"path":"thumbs\/ID_VG%40VDS-100mV.png","width":240,"height":180},"objects":[{"path":"ID_VG%40VDS-100mV.png","image":{"path":"slides\/ID_VG%40VDS-100mV.png","width":879,"height":572},"imageCaption":"<h5>ID VG@VDS=100mV<\/h5>","thumb":{"path":"thumbs\/ID_VG%40VDS-100mV.png","width":240,"height":180},"fileSize":79729,"epochDate":1505767782711,"name":"ID_VG@VDS-100mV.png","fileDate":"2017-09-18T17:49:42.711Z","category":"image"},{"path":"sigmaID_VG.png","image":{"path":"slides\/sigmaID_VG.png","width":946,"height":695},"imageCaption":"<h5>sigmaID VG<\/h5>","thumb":{"path":"thumbs\/sigmaID_VG.png","width":240,"height":180},"fileSize":284820,"epochDate":1506531825713,"name":"sigmaID_VG.png","fileDate":"2017-09-27T14:03:45.713Z","category":"image"},{"path":"sigmaID_VGsame_1OverSqrtWL.png","image":{"path":"slides\/sigmaID_VGsame_1OverSqrtWL.png","width":1000,"height":282},"imageCaption":"<h5>sigmaID VGsame 1OverSqrtWL<\/h5>","thumb":{"path":"thumbs\/sigmaID_VGsame_1OverSqrtWL.png","width":240,"height":180},"fileSize":54936,"epochDate":1506535056850,"name":"sigmaID_VGsame_1OverSqrtWL.png","fileDate":"2017-09-27T14:57:36.850Z","category":"image"},{"path":"sigmaVTH_1overSqrtWL.png","image":{"path":"slides\/sigmaVTH_1overSqrtWL.png","width":936,"height":542},"imageCaption":"<h5>sigmaVTH 1overSqrtWL<\/h5>","thumb":{"path":"thumbs\/sigmaVTH_1overSqrtWL.png","width":240,"height":180},"fileSize":49363,"epochDate":1506622109047,"name":"sigmaVTH_1overSqrtWL.png","fileDate":"2017-09-28T15:08:29.47Z","category":"image"},{"path":"sigmaBETA_1overSqrtWL.png","image":{"path":"slides\/sigmaBETA_1overSqrtWL.png","width":1000,"height":598},"imageCaption":"<h5>sigmaBETA 1overSqrtWL<\/h5>","thumb":{"path":"thumbs\/sigmaBETA_1overSqrtWL.png","width":240,"height":180},"fileSize":55000,"epochDate":1506715590639,"name":"sigmaBETA_1overSqrtWL.png","fileDate":"2017-09-29T17:06:30.639Z","category":"image"},{"path":"sigmaVTHWLdependence.png","image":{"path":"slides\/sigmaVTHWLdependence.png","width":1000,"height":597},"imageCaption":"<h5>sigmaVTHWLdependence<\/h5>","thumb":{"path":"thumbs\/sigmaVTHWLdependence.png","width":240,"height":180},"fileSize":116221,"epochDate":1507237545825,"name":"sigmaVTHWLdependence.png","fileDate":"2017-10-05T18:05:45.825Z","category":"image"},{"path":"todas_lin.png","image":{"path":"slides\/todas_lin.png","width":1000,"height":539},"imageCaption":"<h5>todas lin<\/h5>","thumb":{"path":"thumbs\/todas_lin.png","width":240,"height":180},"fileSize":51380,"epochDate":1509469819535,"name":"todas_lin.png","fileDate":"2017-10-31T15:10:19.535Z","category":"image"},{"path":"secondderiv_problem.png","image":{"path":"slides\/secondderiv_problem.png","width":1000,"height":517},"imageCaption":"<h5>secondderiv problem<\/h5>","thumb":{"path":"thumbs\/secondderiv_problem.png","width":240,"height":180},"fileSize":15771,"epochDate":1513960551348,"name":"secondderiv_problem.png","fileDate":"2017-12-22T14:35:51.348Z","category":"image"},{"path":"secondderiv_problem_zoom.png","image":{"path":"slides\/secondderiv_problem_zoom.png","width":1000,"height":538},"imageCaption":"<h5>secondderiv problem zoom<\/h5>","thumb":{"path":"thumbs\/secondderiv_problem_zoom.png","width":240,"height":180},"fileSize":79952,"epochDate":1513962876454,"name":"secondderiv_problem_zoom.png","fileDate":"2017-12-22T15:14:36.454Z","category":"image"}],"name":"IDVGVD100mV","fileDate":"2018-01-28T08:43:41.468Z"}